alias_cd/__init__.py
alias_cd/cli.py
alias_cd/config.py
alias_cd/py.typed
alias_cd-0.0.1.dist-info/LICENSE
alias_cd-0.0.1.dist-info/METADATA
alias_cd-0.0.1.dist-info/WHEEL
alias_cd-0.0.1.dist-info/entry_points.txt
alias_cd-0.0.1.dist-info/top_level.txt
alias_cd-0.0.1.dist-info/RECORD
